trajax/__init__.py
trajax/factory.py
trajax/jax.py
trajax/namespace.py
trajax/numpy.py
trajax/collectors/__init__.py
trajax/collectors/access.py
trajax/collectors/factory.py
trajax/collectors/obstacles.py
trajax/collectors/registry.py
trajax/collectors/risk.py
trajax/collectors/state.py
trajax/costs/__init__.py
trajax/costs/accelerated.py
trajax/costs/basic.py
trajax/costs/factory.py
trajax/costs/boundary/__init__.py
trajax/costs/boundary/accelerated.py
trajax/costs/boundary/basic.py
trajax/costs/collision/__init__.py
trajax/costs/collision/accelerated.py
trajax/costs/collision/basic.py
trajax/costs/combined/__init__.py
trajax/costs/combined/accelerated.py
trajax/costs/combined/basic.py
trajax/costs/combined/common.py
trajax/costs/distance/__init__.py
trajax/costs/distance/accelerated.py
trajax/costs/distance/basic.py
trajax/costs/distance/common.py
trajax/costs/risk/__init__.py
trajax/costs/risk/base.py
trajax/costs/risk/factory.py
trajax/metrics/__init__.py
trajax/metrics/collision.py
trajax/metrics/error.py
trajax/metrics/factory.py
trajax/metrics/registry.py
trajax/models/__init__.py
trajax/models/factory.py
trajax/models/bicycle/__init__.py
trajax/models/bicycle/accelerated.py
trajax/models/bicycle/basic.py
trajax/models/integrator/__init__.py
trajax/models/integrator/accelerated.py
trajax/models/integrator/basic.py
trajax/mpcc/__init__.py
trajax/mpcc/accelerated.py
trajax/mpcc/basic.py
trajax/mpcc/common.py
trajax/mppi/__init__.py
trajax/mppi/accelerated.py
trajax/mppi/basic.py
trajax/mppi/common.py
trajax/mppi/savgol/__init__.py
trajax/mppi/savgol/accelerated.py
trajax/mppi/savgol/basic.py
trajax/obstacles/__init__.py
trajax/obstacles/accelerated.py
trajax/obstacles/basic.py
trajax/obstacles/common.py
trajax/obstacles/factory.py
trajax/obstacles/assignment/__init__.py
trajax/obstacles/assignment/accelerated.py
trajax/obstacles/assignment/basic.py
trajax/obstacles/dynamic/__init__.py
trajax/obstacles/dynamic/accelerated.py
trajax/obstacles/dynamic/basic.py
trajax-0.1.14.dist-info/METADATA
trajax-0.1.14.dist-info/WHEEL
trajax-0.1.14.dist-info/licenses/LICENSE
trajax-0.1.14.dist-info/RECORD
